okta_oauth2/__init__.py
okta_oauth2/apps.py
okta_oauth2/backend.py
okta_oauth2/conf.py
okta_oauth2/decorators.py
okta_oauth2/exceptions.py
okta_oauth2/middleware.py
okta_oauth2/tests/settings.py
okta_oauth2/tests/templates/okta_oauth2/login.html
okta_oauth2/tests/test_backend.py
okta_oauth2/tests/test_conf.py
okta_oauth2/tests/test_decorator.py
okta_oauth2/tests/test_middleware.py
okta_oauth2/tests/test_token_validator.py
okta_oauth2/tests/test_views.py
okta_oauth2/tests/urls.py
okta_oauth2/tests/utils.py
okta_oauth2/tokens.py
okta_oauth2/urls.py
okta_oauth2/views.py
django_okta_auth-0.8.0.dist-info/LICENSE
django_okta_auth-0.8.0.dist-info/WHEEL
django_okta_auth-0.8.0.dist-info/METADATA
django_okta_auth-0.8.0.dist-info/RECORD
