Metadata-Version: 2.1
Name: django-okta-auth
Version: 0.8.0
Summary: Django Authentication for Okta OpenID
Home-page: https://github.com/AzMoo/django-okta-auth
License: MIT
Author: Matt Magin
Author-email: matt.magin@cmv.com.au
Requires-Python: >=3.6,<4.0
Classifier: License :: OSI Approved :: MIT License
Classifier: Programming Language :: Python :: 3
Classifier: Programming Language :: Python :: 3.6
Classifier: Programming Language :: Python :: 3.7
Classifier: Programming Language :: Python :: 3.8
Classifier: Programming Language :: Python :: 3.9
Requires-Dist: Django (>=1.11.0)
Requires-Dist: PyJWT (>=1.7.1,<2.0.0)
Requires-Dist: python-jose[cryptography] (>=3.1.0,<4.0.0)
Requires-Dist: requests (>=2.22.0,<3.0.0)
Project-URL: Repository, https://github.com/AzMoo/django-okta-auth
